[ {
  "id" : "ddf6e8d9-f6cf-a715-c3a1-99a2383ca3c1",
  "name" : "caption",
  "display_width" : null,
  "label" : "Caption",
  "required" : false,
  "locked" : false,
  "validation_regex" : "",
  "allow_new_line" : false,
  "show_emoji_picker" : false,
  "type" : "text",
  "default" : "Follow the map for directions"
}, {
  "id" : "c311e1fd-67e5-f38b-1d44-c6d9fc25c807",
  "name" : "title",
  "display_width" : null,
  "label" : "Title",
  "required" : false,
  "locked" : false,
  "validation_regex" : "",
  "allow_new_line" : false,
  "show_emoji_picker" : false,
  "type" : "text",
  "default" : "Visit Our Office!"
}, {
  "id" : "fd232289-d45c-97f0-7e2c-f4a2bc0908d7",
  "name" : "text",
  "display_width" : null,
  "label" : "Text",
  "required" : false,
  "locked" : false,
  "type" : "richtext",
  "default" : "<p>Felis placerat gravida sed nibh id purus. Dictum tristique sagittis lobortis sed. Fames fermentum viverra aliquet volutpat. Fames fermentum viverra aliquet volutpat.</p>"
}, {
  "id" : "d8a06c91-6bef-2e0f-821a-d9cb3a0d0da3",
  "name" : "image_field",
  "display_width" : null,
  "label" : "Image",
  "required" : false,
  "locked" : false,
  "responsive" : true,
  "resizable" : true,
  "show_loading" : false,
  "type" : "image",
  "default" : {
    "size_type" : "auto",
    "src" : "",
    "alt" : null,
    "loading" : "lazy"
  }
} ]